openhydroponics/__init__.py
openhydroponics/cli.py
openhydroponics/msg_pipe.py
openhydroponics/signal.py
openhydroponics/base/__init__.py
openhydroponics/base/endpoint.py
openhydroponics/base/node.py
openhydroponics/base/node_manager.py
openhydroponics/conf/dbus/com.openhydroponics.conf
openhydroponics/conf/systemd/openhydroponicsd.service
openhydroponics/dbus/__init__.py
openhydroponics/dbus/endpoint.py
openhydroponics/dbus/node.py
openhydroponics/dbus/node_manager.py
openhydroponics/lib/__init__.py
openhydroponics/lib/dbus.py
openhydroponics/net/__init__.py
openhydroponics/net/endpoint.py
openhydroponics/net/msg.py
openhydroponics/net/node.py
openhydroponics/net/node_manager.py
openhydroponics/net/phyinterface.py
openhydroponics/service/__init__.py
openhydroponics/service/endpoint.py
openhydroponics/service/main.py
openhydroponics-0.6.0.dist-info/METADATA
openhydroponics-0.6.0.dist-info/WHEEL
openhydroponics-0.6.0.dist-info/entry_points.txt
openhydroponics-0.6.0.dist-info/licenses/LICENSE
openhydroponics-0.6.0.dist-info/RECORD
