Metadata-Version: 2.4
Name: openhydroponics
Version: 0.6.0
Summary: Library for accessing OpenHydroponics hardware nodes
Author-email: Micke Prag <micke.prag@gmail.com>
License-File: LICENSE
Classifier: Development Status :: 2 - Pre-Alpha
Classifier: Intended Audience :: Developers
Classifier: License :: OSI Approved :: Mozilla Public License 2.0 (MPL 2.0)
Classifier: Operating System :: OS Independent
Classifier: Programming Language :: Python
Classifier: Programming Language :: Python :: 3
Classifier: Programming Language :: Python :: 3 :: Only
Classifier: Programming Language :: Python :: 3.10
Requires-Python: <4.0,>=3.10
Requires-Dist: click>=8.1.8
Requires-Dist: dbus-fast>=2.44.1
Requires-Dist: id>=1.5.0
Requires-Dist: plum-dispatch<2.3,>=2
Requires-Dist: pypostcard>=0.1.0
Requires-Dist: pyserial>=3.5
Requires-Dist: python-can>=4.4.2
